odoo/addons/product_weight/README.rst
odoo/addons/product_weight/__init__.py
odoo/addons/product_weight/__manifest__.py
odoo/addons/product_weight/i18n/ca.po
odoo/addons/product_weight/i18n/de.po
odoo/addons/product_weight/i18n/es.po
odoo/addons/product_weight/i18n/fr.po
odoo/addons/product_weight/i18n/hr.po
odoo/addons/product_weight/i18n/it.po
odoo/addons/product_weight/i18n/nl_NL.po
odoo/addons/product_weight/i18n/product_weight.pot
odoo/addons/product_weight/i18n/sl.po
odoo/addons/product_weight/models/__init__.py
odoo/addons/product_weight/models/bom.py
odoo/addons/product_weight/static/description/icon.png
odoo/addons/product_weight/tests/__init__.py
odoo/addons/product_weight/tests/test_compute_bom_weight.py
odoo/addons/product_weight/views/product_view.xml
odoo/addons/product_weight/wizard/__init__.py
odoo/addons/product_weight/wizard/product_weight_update.py
odoo/addons/product_weight/wizard/product_weight_update_view.xml
odoo11_addon_product_weight-11.0.1.0.0.99.dev5.dist-info/METADATA
odoo11_addon_product_weight-11.0.1.0.0.99.dev5.dist-info/WHEEL
odoo11_addon_product_weight-11.0.1.0.0.99.dev5.dist-info/top_level.txt
odoo11_addon_product_weight-11.0.1.0.0.99.dev5.dist-info/RECORD
